velour/__init__.py
velour/datasets.py
velour/geometry.py
velour/persistence.py
velour-2020.11.18.dist-info/LICENCE
velour-2020.11.18.dist-info/METADATA
velour-2020.11.18.dist-info/WHEEL
velour-2020.11.18.dist-info/top_level.txt
velour-2020.11.18.dist-info/RECORD
