Metadata-Version: 2.1
Name: velour
Version: 2020.11.18
Summary: Topological inference from point clouds with persistent homology
Home-page: https://github.com/raphaeltinarrage/velour
Author: Raphaël Tinarrage
Author-email: raphael.tinarrage@gmail.com
License: UNKNOWN
Platform: UNKNOWN
Classifier: Programming Language :: Python :: 3
Classifier: License :: OSI Approved :: MIT License
Classifier: Operating System :: OS Independent
Requires-Python: >=3.6
Requires-Dist: gudhi
Requires-Dist: numpy
Requires-Dist: sklearn
Requires-Dist: scipy
Requires-Dist: matplotlib
